{
  "id": "divinejourney2",
  "display_name": "Divine Journey 2",
  "description": "Divine Journey 2 modpack with OmkalityCore",
  "ignored_paths": [
    "crash-reports/",
    "dumps/",
    "journeymap/",
    "local/",
    "logs/",
    "saves/",
    "screenshots/",
    "BotaniaVars.dat",
    "crafttweaker.log",
    "knownkeys.txt",
    "roots.log",
    "usercache.json",
    "usernamecache.json"
  ],
  "soft_managed_paths": [
    "config/",
    "options.txt"
  ],
  "delete_extra_files_in_managed_paths": true
}
